explorex/__init__.py
explorex/core.py
explorex-0.1.1.dist-info/METADATA
explorex-0.1.1.dist-info/WHEEL
explorex-0.1.1.dist-info/licenses/LICENSE
explorex-0.1.1.dist-info/RECORD
