Metadata-Version: 2.4
Name: explorex
Version: 0.1.1
Summary: Tiny action-selection helpers (explore/exploit/epsilon-greedy).
Author: Your Name
License: MIT
License-File: LICENSE
Classifier: License :: OSI Approved :: MIT License
Classifier: Programming Language :: Python :: 3
Requires-Python: >=3.8
